{"success":true,"battle_id":34,"battle_phase":"final","is_token_match":false,"battle_winner":"red","times":{"timestamp":{"betting_started":1417584828,"battle_started":1417585090,"battle_ended":1417585289},"current":{"duration":154,"value":"2 minutes, 34 seconds"}},"blue":{"team_string":"Dewgong, Roselia, Claydol","team":{"Dewgong":{"dexNumber":87,"name":"Dewgong"},"Roselia":{"dexNumber":315,"name":"Roselia"},"Claydol":{"dexNumber":344,"name":"Claydol"}},"bets":{"total":51266,"odds":{"decimal":0.20009362930597,"value":"5:1"},"bets":{"fanshengchen":{"balance":0,"amount":25000},"your_balance_is_999999":{"balance":0,"amount":3642},"lonsfor":{"balance":0,"amount":2154},"fiercedeity11":{"balance":0,"amount":1657},"rtsrangel":{"balance":0,"amount":1640},"mavossa1":{"balance":0,"amount":1500},"manomanitee":{"balance":0,"amount":1300},"blackthorngymleaderclair":{"balance":0,"amount":1111},"julianjmoss":{"balance":0,"amount":1006},"anarchysisters":{"balance":0,"amount":1000},"couchington":{"balance":0,"amount":1000},"godoftrollers":{"balance":0,"amount":1000},"grazinbullets":{"balance":0,"amount":1000},"overratedfishy":{"balance":0,"amount":1000},"pokemarster":{"balance":0,"amount":1000},"ernturn11":{"balance":0,"amount":926},"aysz88":{"balance":0,"amount":500},"cyber226":{"balance":0,"amount":500},"joshuaisadolphin":{"balance":0,"amount":500},"mustangcz":{"balance":0,"amount":500},"shinypokerusmirageisland":{"balance":0,"amount":500},"janno27":{"balance":0,"amount":387},"misiekf71":{"balance":0,"amount":387},"thenewbiestreamer":{"balance":0,"amount":349},"ascisana":{"balance":0,"amount":275},"pseudoeternal":{"balance":0,"amount":250},"alanawesker014":{"balance":0,"amount":200},"linear_equation":{"balance":0,"amount":115},"gloamingdusk":{"balance":0,"amount":100},"mrbastatwitch":{"balance":0,"amount":100},"pawed85":{"balance":0,"amount":100},"rekartsfsx":{"balance":0,"amount":100},"thesworduser":{"balance":0,"amount":100},"traevus":{"balance":0,"amount":100},"wafflecookie":{"balance":0,"amount":100},"x42bn6":{"balance":0,"amount":100},"coolyon":{"balance":0,"amount":57},"queenpocketmonsta":{"balance":0,"amount":10}}}},"red":{"team_string":"Giratina, Staryu, Cherubi","team":{"Giratina":{"dexNumber":487,"name":"Giratina"},"Staryu":{"dexNumber":120,"name":"Staryu"},"Cherubi":{"dexNumber":420,"name":"Cherubi"}},"bets":{"total":10258,"odds":{"decimal":4.9976603626438,"value":"1:0.2"},"bets":{"chauzu_vgc":{"balance":0,"amount":5000},"thewlllofd":{"balance":0,"amount":1000},"knubtw":{"balance":0,"amount":999},"pikawoof29":{"balance":0,"amount":732},"jeffinky":{"balance":0,"amount":500},"the_chef1337":{"balance":0,"amount":500},"metalthrasher11":{"balance":0,"amount":300},"kuzari":{"balance":0,"amount":250},"atma505":{"balance":0,"amount":200},"zombiemonkey7":{"balance":0,"amount":200},"hunangren":{"balance":0,"amount":150},"dorvanritos":{"balance":0,"amount":111},"hugo_mcchunky":{"balance":0,"amount":100},"valand43":{"balance":0,"amount":100},"nippyswiff":{"balance":0,"amount":50},"the_beefcube":{"balance":0,"amount":44},"zonnoser":{"balance":0,"amount":10},"duscoda":{"balance":0,"amount":6},"muchrng":{"balance":0,"amount":5},"jacenboy":{"balance":0,"amount":1}}}}}